{
  "id": "1950323",
  "name": "wangyiyun",
  "font_family": "iconfont",
  "css_prefix_text": "icon",
  "description": "网易云",
  "glyphs": [
    {
      "icon_id": "3763998",
      "name": "赞",
      "font_class": "weibiaoti-",
      "unicode": "e60d",
      "unicode_decimal": 58893
    },
    {
      "icon_id": "3090318",
      "name": "人物",
      "font_class": "character",
      "unicode": "e62e",
      "unicode_decimal": 58926
    },
    {
      "icon_id": "3216055",
      "name": "转发",
      "font_class": "icon--",
      "unicode": "e70d",
      "unicode_decimal": 59149
    },
    {
      "icon_id": "4406892",
      "name": "时钟",
      "font_class": "shizhong",
      "unicode": "e650",
      "unicode_decimal": 58960
    },
    {
      "icon_id": "5158031",
      "name": "消息",
      "font_class": "xiaoxi-",
      "unicode": "e60c",
      "unicode_decimal": 58892
    },
    {
      "icon_id": "8348163",
      "name": "下载",
      "font_class": "xiazai",
      "unicode": "e723",
      "unicode_decimal": 59171
    },
    {
      "icon_id": "5217275",
      "name": "钢琴",
      "font_class": "guigetubiao-",
      "unicode": "e611",
      "unicode_decimal": 58897
    },
    {
      "icon_id": "15282695",
      "name": "钢琴02",
      "font_class": "gangqin02",
      "unicode": "e6c8",
      "unicode_decimal": 59080
    },
    {
      "icon_id": "11757073",
      "name": "钢琴",
      "font_class": "gangqin",
      "unicode": "e739",
      "unicode_decimal": 59193
    },
    {
      "icon_id": "7147175",
      "name": "下拉",
      "font_class": "jiantou",
      "unicode": "e614",
      "unicode_decimal": 58900
    },
    {
      "icon_id": "5270852",
      "name": "收 藏-产品详情",
      "font_class": "shoucang",
      "unicode": "e613",
      "unicode_decimal": 58899
    },
    {
      "icon_id": "5330820",
      "name": "圆点",
      "font_class": "yuandian",
      "unicode": "e7c2",
      "unicode_decimal": 59330
    },
    {
      "icon_id": "4328008",
      "name": "播放",
      "font_class": "bofang",
      "unicode": "e645",
      "unicode_decimal": 58949
    },
    {
      "icon_id": "11405795",
      "name": "听歌",
      "font_class": "icon-test",
      "unicode": "e618",
      "unicode_decimal": 58904
    },
    {
      "icon_id": "1132491",
      "name": "左箭头",
      "font_class": "zuojiantou",
      "unicode": "e647",
      "unicode_decimal": 58951
    },
    {
      "icon_id": "15997009",
      "name": "左箭头",
      "font_class": "zuojiantou-copy",
      "unicode": "e648",
      "unicode_decimal": 58952
    },
    {
      "icon_id": "15997011",
      "name": "左箭头",
      "font_class": "zuojiantou-copy1",
      "unicode": "e649",
      "unicode_decimal": 58953
    },
    {
      "icon_id": "15997016",
      "name": "左箭头",
      "font_class": "zuojiantou-copy2",
      "unicode": "e64a",
      "unicode_decimal": 58954
    },
    {
      "icon_id": "15997017",
      "name": "左箭头",
      "font_class": "zuojiantou-copy3",
      "unicode": "e64b",
      "unicode_decimal": 58955
    },
    {
      "icon_id": "15997018",
      "name": "左箭头",
      "font_class": "zuojiantou-copy-copy",
      "unicode": "e64c",
      "unicode_decimal": 58956
    },
    {
      "icon_id": "5640058",
      "name": "搜索",
      "font_class": "sousuo",
      "unicode": "e627",
      "unicode_decimal": 58919
    }
  ]
}
